aiocarbon/__init__.py
aiocarbon/context.py
aiocarbon/metric.py
aiocarbon/setup.py
aiocarbon/version.py
aiocarbon/protocol/__init__.py
aiocarbon/protocol/base.py
aiocarbon/protocol/buffer.py
aiocarbon/protocol/pickle.py
aiocarbon/protocol/tcp.py
aiocarbon/protocol/udp.py
aiocarbon/storage/__init__.py
aiocarbon/storage/base.py
aiocarbon/storage/raw.py
aiocarbon/storage/total.py
aiocarbon-0.15.3.dist-info/LICENCE
aiocarbon-0.15.3.dist-info/LICENCE.md
aiocarbon-0.15.3.dist-info/METADATA
aiocarbon-0.15.3.dist-info/WHEEL
aiocarbon-0.15.3.dist-info/top_level.txt
aiocarbon-0.15.3.dist-info/RECORD
