Metadata-Version: 2.1
Name: aiocarbon
Version: 0.15.3
Summary: Asynchronous client for carbon.
Home-page: http://github.com/mosquito/aiocarbon
Author: Dmitry Orlov <me@mosquito.su>
Author-email: me@mosquito.su
License: Apache 2
Keywords: aio,python,asyncio,carbon,graphite,client
Classifier: Development Status :: 4 - Beta
Classifier: Intended Audience :: Developers
Classifier: License :: OSI Approved :: Apache Software License
Classifier: Natural Language :: English
Classifier: Natural Language :: Russian
Classifier: Operating System :: POSIX :: Linux
Classifier: Operating System :: MacOS :: MacOS X
Classifier: Programming Language :: Cython
Classifier: Programming Language :: Python
Classifier: Programming Language :: Python :: 3 :: Only
Classifier: Programming Language :: Python :: 3.4
Classifier: Programming Language :: Python :: 3.5
Classifier: Programming Language :: Python :: 3.6
Classifier: Topic :: Software Development :: Libraries
Classifier: Topic :: System
Classifier: Topic :: System :: Operating System
Provides: aiocarbon
Requires-Python: >=3.5, <4
License-File: LICENCE
License-File: LICENCE.md
Requires-Dist: immutables
